MANIFEST.in
README.rst
setup.py
hitchquickstart/__init__.py
hitchquickstart/commandline.py
hitchquickstart/questions.yml
hitchquickstart/utils.py
hitchquickstart.egg-info/PKG-INFO
hitchquickstart.egg-info/SOURCES.txt
hitchquickstart.egg-info/dependency_links.txt
hitchquickstart.egg-info/entry_points.txt
hitchquickstart.egg-info/not-zip-safe
hitchquickstart.egg-info/requires.txt
hitchquickstart.egg-info/top_level.txt
hitchquickstart/templates/README.rst.jinja2
hitchquickstart/templates/all.settings.jinja2
hitchquickstart/templates/ci.settings.jinja2
hitchquickstart/templates/engine.py.jinja2
hitchquickstart/templates/stub.test.jinja2
hitchquickstart/templates/system.packages.jinja2
hitchquickstart/templates/tdd.settings.jinja2